aiojsonrpc/__init__.py
aiojsonrpc/client.py
aiojsonrpc/constants.py
aiojsonrpc/exception.py
aiojsonrpc/request_handler.py
aiojsonrpc/service.py
aiojsonrpc/service_mixin.py
aiojsonrpc/util.py
aiojsonrpc/serializer/__init__.py
aiojsonrpc/serializer/factory.py
aiojsonrpc/serializer/json.py
aiojsonrpc/serializer/msgpack.py
aiojsonrpc-0.0.6.dist-info/DESCRIPTION.rst
aiojsonrpc-0.0.6.dist-info/METADATA
aiojsonrpc-0.0.6.dist-info/RECORD
aiojsonrpc-0.0.6.dist-info/WHEEL
aiojsonrpc-0.0.6.dist-info/metadata.json
aiojsonrpc-0.0.6.dist-info/top_level.txt
