Metadata-Version: 2.0
Name: aiojsonrpc
Version: 0.0.6
Summary: JSON-RPC library to use in asynchronous JSON-RPC services
Home-page: https://github.com/f0t0n/aiojsonrpc/
Author: Eugene Naydenov
Author-email: t.34.oxygen+github+aiojsonrpc@gmail.com
License: Apache 2
Platform: UNKNOWN
Classifier: License :: OSI Approved :: Apache Software License
Classifier: Intended Audience :: Developers
Classifier: Development Status :: 4 - Beta
Classifier: Operating System :: OS Independent
Classifier: Programming Language :: Python
Classifier: Programming Language :: Python :: 3
Classifier: Programming Language :: Python :: 3.5
Classifier: Programming Language :: Python :: Implementation :: CPython
Classifier: Topic :: Internet :: WWW/HTTP :: Dynamic Content
Classifier: Topic :: Software Development :: Libraries :: Python Modules
Requires-Dist: aiohttp (>=0.21.5)
Requires-Dist: msgpack-python (>=0.4.7)
Requires-Dist: ujson (>=1.35)
